mcp_seniverse_weather_pengliu/__init__.py
mcp_seniverse_weather_pengliu/__main__.py
mcp_seniverse_weather_pengliu/server.py
mcp_seniverse_weather_pengliu-1.0.0.dist-info/METADATA
mcp_seniverse_weather_pengliu-1.0.0.dist-info/WHEEL
mcp_seniverse_weather_pengliu-1.0.0.dist-info/entry_points.txt
mcp_seniverse_weather_pengliu-1.0.0.dist-info/RECORD
